{
  "__type__": "dragonBones.DragonBonesAsset",
  "_name": "xiongmao_ske",
  "_objFlags": 0,
  "_rawFiles": null,
  "_dragonBonesJson": "{\"frameRate\":24,\"version\":\"4.5\",\"isGlobal\":0,\"name\":\"xiongmao\",\"armature\":[{\"frameRate\":24,\"defaultActions\":[{\"gotoAndPlay\":\"xiongmao\"}],\"animation\":[{\"playTimes\":0,\"slot\":[],\"ik\":[],\"frame\":[],\"ffd\":[],\"name\":\"xiongmao\",\"duration\":96,\"bone\":[{\"frame\":[{\"transform\":{},\"duration\":96}],\"name\":\"root\"},{\"frame\":[{\"transform\":{},\"duration\":96}],\"name\":\"xiongmao\"},{\"frame\":[{\"tweenEasing\":0,\"transform\":{},\"duration\":24},{\"tweenEasing\":0,\"transform\":{\"skX\":-4,\"skY\":-4},\"duration\":24},{\"tweenEasing\":0,\"transform\":{},\"duration\":24},{\"tweenEasing\":0,\"transform\":{\"skX\":-4,\"skY\":-4},\"duration\":24},{\"transform\":{},\"duration\":0}],\"name\":\"xiongmao_tou\"},{\"frame\":[{\"tweenEasing\":0,\"transform\":{},\"duration\":12},{\"tweenEasing\":0,\"transform\":{\"skX\":-8.997,\"skY\":-8.997},\"duration\":12},{\"tweenEasing\":0,\"transform\":{},\"duration\":12},{\"tweenEasing\":0,\"transform\":{\"skX\":-8.997,\"skY\":-8.997},\"duration\":12},{\"tweenEasing\":0,\"transform\":{},\"duration\":12},{\"tweenEasing\":0,\"transform\":{\"skX\":-8.997,\"skY\":-8.997},\"duration\":12},{\"tweenEasing\":0,\"transform\":{},\"duration\":12},{\"tweenEasing\":0,\"transform\":{\"skX\":-8.997,\"skY\":-8.997},\"duration\":12},{\"transform\":{},\"duration\":0}],\"name\":\"xiongmao_shou_01\"},{\"frame\":[{\"tweenEasing\":0,\"transform\":{\"skX\":11.001,\"skY\":11.001,\"scX\":0.9},\"duration\":6},{\"tweenEasing\":0,\"transform\":{\"skX\":-28.999,\"skY\":-28.999,\"scX\":0.9},\"duration\":6},{\"tweenEasing\":0,\"transform\":{\"skX\":-15.999,\"skY\":-15.999},\"duration\":6},{\"tweenEasing\":0,\"transform\":{\"skX\":-2.999,\"skY\":-2.999,\"scX\":1.1},\"duration\":6},{\"tweenEasing\":0,\"transform\":{\"skX\":11.001,\"skY\":11.001,\"scX\":0.9},\"duration\":6},{\"tweenEasing\":0,\"transform\":{\"skX\":-28.999,\"skY\":-28.999,\"scX\":0.9},\"duration\":6},{\"tweenEasing\":0,\"transform\":{\"skX\":-15.999,\"skY\":-15.999},\"duration\":6},{\"tweenEasing\":0,\"transform\":{\"skX\":-2.999,\"skY\":-2.999,\"scX\":1.1},\"duration\":6},{\"tweenEasing\":0,\"transform\":{\"skX\":11.001,\"skY\":11.001,\"scX\":0.9},\"duration\":6},{\"tweenEasing\":0,\"transform\":{\"skX\":-28.999,\"skY\":-28.999,\"scX\":0.9},\"duration\":6},{\"tweenEasing\":0,\"transform\":{\"skX\":-15.999,\"skY\":-15.999},\"duration\":6},{\"tweenEasing\":0,\"transform\":{\"skX\":-2.999,\"skY\":-2.999,\"scX\":1.1},\"duration\":6},{\"transform\":{\"skX\":11.001,\"skY\":11.001,\"scX\":0.9},\"duration\":24}],\"name\":\"xiongmao_shou_02\"}]}],\"skin\":[{\"slot\":[{\"display\":[{\"type\":\"image\",\"transform\":{\"y\":-4.3167,\"skX\":90,\"skY\":90,\"x\":30.8752},\"name\":\"xiongmao_tou\",\"path\":\"xiongmao_tou\"}],\"name\":\"xiongmao_tou\"},{\"display\":[{\"type\":\"image\",\"transform\":{\"y\":-18.0153,\"skX\":-54.447,\"skY\":-54.447,\"x\":17.8739},\"name\":\"xiongmao_shou_01\",\"path\":\"xiongmao_shou_01\"}],\"name\":\"xiongmao_shou_01\"},{\"display\":[{\"type\":\"image\",\"transform\":{},\"name\":\"xiongmao_shenti\",\"path\":\"xiongmao_shenti\"}],\"name\":\"xiongmao_shenti\"},{\"display\":[{\"type\":\"image\",\"transform\":{\"y\":31.4025},\"name\":\"xiongmao_yinying\",\"path\":\"xiongmao_yinying\"}],\"name\":\"xiongmao_yinying\"},{\"display\":[{\"type\":\"image\",\"transform\":{\"y\":-6.7568,\"skX\":-65.259,\"skY\":-65.259,\"x\":27.0883},\"name\":\"xiongmao_shou_02\",\"path\":\"xiongmao_shou_02\"}],\"name\":\"xiongmao_shou_02\"}],\"name\":\"\"}],\"type\":\"Armature\",\"aabb\":{\"x\":-86,\"y\":-76.57517086210737,\"width\":177.49973447689877,\"height\":123.47768650410588},\"slot\":[{\"color\":{},\"name\":\"xiongmao_yinying\",\"parent\":\"xiongmao\"},{\"z\":1,\"color\":{},\"name\":\"xiongmao_shenti\",\"parent\":\"xiongmao\"},{\"z\":2,\"color\":{},\"name\":\"xiongmao_shou_01\",\"parent\":\"xiongmao_shou_01\"},{\"z\":3,\"color\":{},\"name\":\"xiongmao_shou_02\",\"parent\":\"xiongmao_shou_02\"},{\"z\":4,\"color\":{},\"name\":\"xiongmao_tou\",\"parent\":\"xiongmao_tou\"}],\"ik\":[],\"name\":\"Armature\",\"bone\":[{\"transform\":{},\"name\":\"root\"},{\"transform\":{},\"name\":\"xiongmao\",\"parent\":\"root\"},{\"length\":24,\"parent\":\"xiongmao\",\"transform\":{\"y\":-14.2,\"skX\":-90,\"skY\":-90,\"x\":-0.5},\"name\":\"xiongmao_tou\"},{\"length\":21,\"parent\":\"xiongmao\",\"transform\":{\"y\":-26.85,\"skX\":54.447,\"skY\":54.447,\"x\":33.45},\"name\":\"xiongmao_shou_01\"},{\"length\":35,\"parent\":\"xiongmao\",\"transform\":{\"y\":-24.3,\"skX\":65.259,\"skY\":65.259,\"x\":-47.6},\"name\":\"xiongmao_shou_02\"}]}]}"
}